{
  "transactions": [
    {
      "id": "772d2159-2f4e-4b52-9add-925c25dff85d",
      "amount": 38,
      "merchant": "星巴克",
      "category": "餐饮",
      "note": "拿铁",
      "time": "2026-05-17",
      "source": "sms",
      "createdAt": "2026-05-17T15:06:40.460Z"
    },
    {
      "id": "67d27f2d-9569-4191-899a-2e21f8e42e39",
      "amount": 286,
      "merchant": "借记卡",
      "category": "其他",
      "note": "",
      "time": "2026-05-15T10:30:00",
      "source": "sms",
      "createdAt": "2026-05-17T15:06:51.442Z"
    },
    {
      "id": "30688729-0d9f-4faf-8238-fbf9c8b06076",
      "amount": 23.5,
      "merchant": "滴滴出行",
      "category": "交通",
      "note": "",
      "time": "2026-05-17",
      "source": "sms",
      "createdAt": "2026-05-17T15:13:35.725Z"
    },
    {
      "id": "f62c4a5c-209f-4284-ae07-145bb67275ca",
      "amount": 42.5,
      "merchant": "美团外卖",
      "category": "餐饮",
      "note": "",
      "time": "2026-05-17",
      "source": "sms",
      "createdAt": "2026-05-17T15:14:51.684Z"
    },
    {
      "id": "71439b83-2e93-4089-9a4e-c9315fd06f4a",
      "amount": 45,
      "merchant": "肯德基",
      "category": "餐饮",
      "note": "",
      "time": "2026-05-17",
      "source": "sms",
      "createdAt": "2026-05-17T15:16:00.675Z"
    }
  ]
}